jupyter_codeserver_proxy/__init__.py
jupyter_codeserver_proxy/bin/code-server.in
jupyter_codeserver_proxy/icons/code-server-logo.svg
jupyter_codeserver_proxy-0.1.0.dist-info/LICENSE
jupyter_codeserver_proxy-0.1.0.dist-info/METADATA
jupyter_codeserver_proxy-0.1.0.dist-info/WHEEL
jupyter_codeserver_proxy-0.1.0.dist-info/entry_points.txt
jupyter_codeserver_proxy-0.1.0.dist-info/top_level.txt
jupyter_codeserver_proxy-0.1.0.dist-info/RECORD
