Metadata-Version: 2.1
Name: jupyter-codeserver-proxy
Version: 0.1.0
Summary: Code-Server for JupyterLab
Home-page: https://github.com/FZJ-JSC/jupyter-codeserver-proxy
Download-URL: https://github.com/FZJ-JSC/jupyter-codeserver-proxy/archive/v0.1.0.tar.gz
Author: Jens Henrik Goebbert
Author-email: j.goebbert@fz-juelich.de
Keywords: jupyter,code-server,jupyterhub,jupyter-server-proxy
Classifier: Programming Language :: Python :: 3
Classifier: License :: OSI Approved :: BSD License
Classifier: Operating System :: OS Independent
Classifier: Framework :: Jupyter
Requires-Python: >=3.6
License-File: LICENSE
Requires-Dist: jupyter-server-proxy (>=3.1.0)
